high_quant/__init__.py
high_quant/data_prep.py
high_quant/financials.py
high_quant/trading.py
high_quant/trend.py
high_quant/util.py
high_quant/visualization.py
high_quant-0.1.0.dist-info/License
high_quant-0.1.0.dist-info/METADATA
high_quant-0.1.0.dist-info/WHEEL
high_quant-0.1.0.dist-info/top_level.txt
high_quant-0.1.0.dist-info/RECORD
