Metadata-Version: 2.1
Name: high-quant
Version: 0.1.0
Summary: Quantitative analysis tools for investment
Home-page: https://github.com/finterstellar/library
Author: Yubin KIM
Author-email: finterstellar@naver.com
License: UNKNOWN
Platform: UNKNOWN
Classifier: Programming Language :: Python :: 3
Classifier: License :: OSI Approved :: MIT License
Classifier: Operating System :: OS Independent
